test/__init__.py
test/test_data.py
test/test_gr4j.py
test/test_hymod.py
test/test_xaj.py
hydromodel-98316507.dist-info/LICENSE
hydromodel-98316507.dist-info/METADATA
hydromodel-98316507.dist-info/WHEEL
hydromodel-98316507.dist-info/top_level.txt
hydromodel-98316507.dist-info/RECORD
