Metadata-Version: 2.1
Name: hydromodel
Version: 98316507
Summary: xin an jiang
Home-page: https://github.com/iHeadWater/Process_HydroXAJ
Author: Ouyang_Wenyu
Author-email: 
License: GPLv3
Platform: any
Requires-Python: >=3.7
License-File: LICENSE
